mripy/__init__.py
mripy/__version__
mripy/_with_pylab.py
mripy/afni.py
mripy/dcm.py
mripy/decoding.py
mripy/dependency.py
mripy/dicom.py
mripy/dicom_report.py
mripy/encoding.py
mripy/evaluation.py
mripy/headmotion.py
mripy/math.py
mripy/paraproc.py
mripy/preprocess.py
mripy/six.py
mripy/slicetiming.py
mripy/stats.py
mripy/timecourse.py
mripy/utils.py
mripy/vis.py
mripy/data/__init__.py
mripy/data/align_ants_presets/boldref-mni_registration_precise_000.json
mripy/data/align_ants_presets/default.json
mripy/data/align_ants_presets/t1w-epi_huber_layerfmri.json
mripy/data/align_ants_presets/t1w-mni_registration_precise_000.json
mripy/data/align_ants_presets/test.json
mripy/data/atlas/benson14.json
mripy/data/atlas/wang15.json
mripy/io/__init__.py
mripy/io/freesurfer.py
mripy/io/gifti.py
mripy/io/niml.py
mripy/matlab/inpolyhedron.m
mripy/matlab/mripy_align_asc.m
mripy/matlab/mripy_average_asc.m
mripy/matlab/mripy_create_hpf_X0.m
mripy/matlab/mripy_dataset2json.m
mripy/matlab/mripy_diagnose_DCM.m
mripy/matlab/mripy_est_from_GCM.m
mripy/matlab/mripy_est_from_PEB.m
mripy/matlab/mripy_est_from_PEB_BMA.m
mripy/matlab/mripy_infer_suma_subject.m
mripy/matlab/mripy_merge_asc.m
mripy/matlab/mripy_normalize_weight.m
mripy/matlab/mripy_plot_DCM.m
mripy/matlab/mripy_range.m
mripy/matlab/mripy_read_asc.m
mripy/matlab/mripy_read_transform.m
mripy/matlab/mripy_trim_init_resp.m
mripy/matlab/mripy_write_asc.m
mripy/matlab/mripy_write_geometry.m
mripy/scripts/__init__.py
mripy/scripts/afni_viewer.py
mripy/scripts/extract_physio.py
mripy/scripts/ipython_wrapper
mripy/scripts/mripy_1dplot.py
mripy/scripts/mripy_4dslice.ipy
mripy/scripts/mripy_align_S2E.ipy
mripy/scripts/mripy_align_anat.ipy
mripy/scripts/mripy_compute_depth.ipy
mripy/scripts/mripy_create_hd_mesh.ipy
mripy/scripts/mripy_curv2dset.ipy
mripy/scripts/mripy_moco.ipy
mripy/scripts/mripy_run_iglesias18.py
mripy/scripts/mripy_run_wang15.py
mripy/scripts/report_parameters.py
mripy/scripts/script_utils.py
mripy/scripts/sort_dicom.py
mripy-0.7.3.dist-info/LICENSE.txt
mripy-0.7.3.dist-info/METADATA
mripy-0.7.3.dist-info/WHEEL
mripy-0.7.3.dist-info/top_level.txt
mripy-0.7.3.dist-info/RECORD
