Metadata-Version: 2.1
Name: mripy
Version: 0.7.3
Summary: High resolution fMRI data analysis in Python, based on AFNI, FreeSurfer, ANTs, and many other tools.
Home-page: https://github.com/herrlich10/mripy
Author: herrlich10
Author-email: herrlich10@gmail.com
Classifier: Programming Language :: Python :: 3
Classifier: Operating System :: OS Independent
Classifier: License :: OSI Approved :: MIT License
Classifier: Intended Audience :: Developers
Classifier: Intended Audience :: Science/Research
Classifier: Topic :: Scientific/Engineering :: Information Analysis
Classifier: Topic :: Software Development :: Libraries
Classifier: Topic :: Utilities
Requires-Python: >=3.6
License-File: LICENSE.txt
